Workbook

Sheet 00_Sommaire
A1: DOSSIER 2 - PLAN DE TRÉSORERIE PRÉVISIONNEL ET GESTION DU BFR
A3: Onglet | B3: Objet de la modélisation | C3: Méthodes & Outils mobilisés | D3: Enseignement clé / Décision
A4: 01_Hypotheses_BFR | B4: Cadre des flux & Délais de paiement | C4: Règles DSO (comptant, 30j, 60j), DPO (30j), TVA 20%, acomptes IS | D4: Mise en place des leviers d'optimisation du fonds de roulement et du BFR.
A5: 02_Budget_Tresorerie | B5: Budget de trésorerie mensuel sur 12 mois | C5: Flux d'exploitation nets, trésorerie glissante, identification des impasses | D5: Identification de l'impasse d'avril à juillet (-40 k€) et plan de refinancement LT.

Sheet 01_Hypotheses_BFR
A1: PARAMÈTRES D'EXPLOITATION & RÈGLES DU BFR
A3: 1. Hypothèses retenues pour la modélisation financière
A4: Paramètre de gestion | B4: Valeur / Modalité | C4: Impact structurel sur le BFR & la liquidité
A5: Taux normal de TVA | B5: 20,0 % | C5: Applicable aux ventes, achats consommés et charges externes déductibles.
A6: Règlement clients (Ventes TTC) | B6: 20 % comptant, 50 % à 30 j, 30 % à 60 j | C6: Allongement du DSO : 30 % du CA TTC rentre à 2 mois d'écart.
A7: Règlement fournisseurs (Achats TTC) | B7: 100 % à 30 jours (M+1) | C7: DPO standard à 30 j : les règlements devancent les grosses créances clients.
A8: Achats matières / marchandises HT | B8: 50,0 % du CA HT mensuel | C8: Approvisionnements variables indexés sur le plan de vente.
A9: Masse salariale nette | B9: 20,0 k€ / mois (payée mois M) | C9: Flux de décaissement fixe incompressible décaissé en fin de mois.
A10: Cotisations sociales (URSSAF/Retraite) | B10: 10,0 k€ / mois (payées à M+1) | C10: Règlement décalé des charges sociales patronales et salariales.
A11: Autres charges externes TTC | B11: 8,0 k€ / mois (payées mois M) | C11: Frais généraux fixes décaissés comptant (loyer, assurances, entretien).
A12: Acomptes Impôt sur les Sociétés (IS) | B12: 5,0 k€ par trimestre | C12: Échéances fiscales trimestrielles en Mars, Juin, Septembre et Décembre.
A13: Investissement matériel | B13: 50,0 k€ TTC en Avril (comptant) | C13: Choc de trésorerie ponctuel financé par erreur sur le cash d'exploitation.
A14: Trésorerie de départ au 01/01 | B14: +25,0 k€ | C14: Encaisse initiale disponible au bilan d'ouverture.
A15: CA HT Novembre N-1 (hypothèse d'amorçage) | B15: 70 | C15: Base de calcul de la tranche à 60 jours des encaissements de janvier (modèle glissant : le premier trimestre dépend des ventes de l'exercice précédent).
A16: CA HT Décembre N-1 (hypothèse d'amorçage) | B16: 65 | C16: Base de calcul des encaissements de janvier/février, du décaissement fournisseurs de janvier et de la TVA nette décaissée en janvier.

Sheet 02_Budget_Tresorerie
A1: PLAN DE TRÉSORERIE MENSUEL GLISSANT SUR 12 MOIS (en k€)
A3: Poste de flux (k€) | B3: Jan | C3: Fév | D3: Mar | E3: Avr | F3: Mai | G3: Juin | H3: Juil | I3: Août | J3: Sep | K3: Oct | L3: Nov | M3: Déc | N3: Total An
A4: Chiffre d'affaires HT prévisionnel | B4: 60 | C4: 65 | D4: 75 | E4: 90 | F4: 110 | G4: 120 | H4: 115 | I4: 80 | J4: 95 | K4: 105 | L4: 110 | M4: 100 | N4: 1125
A5: TOTAL ENCAISSEMENTS TTC (Clients) | B5: =0.2*B4*1.2+0.5*'01_Hypotheses_BFR'!$B$16*1.2+0.3*'01_Hypotheses_BFR'!$B$15*1.2 -> 78.6 | C5: =0.2*C4*1.2+0.5*B4*1.2+0.3*'01_Hypotheses_BFR'!$B$16*1.2 -> 75 | D5: =0.2*D4*1.2+0.5*C4*1.2+0.3*B4*1.2 -> 78.6 | E5: =0.2*E4*1.2+0.5*D4*1.2+0.3*C4*1.2 -> 90 | F5: =0.2*F4*1.2+0.5*E4*1.2+0.3*D4*1.2 -> 107.4 | G5: =0.2*G4*1.2+0.5*F4*1.2+0.3*E4*1.2 -> 127.2 | H5: =0.2*H4*1.2+0.5*G4*1.2+0.3*F4*1.2 -> 139.2 | I5: =0.2*I4*1.2+0.5*H4*1.2+0.3*G4*1.2 -> 131.4 | J5: =0.2*J4*1.2+0.5*I4*1.2+0.3*H4*1.2 -> 112.2 | K5: =0.2*K4*1.2+0.5*J4*1.2+0.3*I4*1.2 -> 111 | ... M5: =0.2*M4*1.2+0.5*L4*1.2+0.3*K4*1.2 -> 127.8 | N5: =SUM(B5:M5) -> 1302
A6: Achats réglés aux fournisseurs (30 j) | B6: =0.5*'01_Hypotheses_BFR'!$B$16*1.2 -> 39 | C6: =0.5*B4*1.2 -> 36 | D6: =0.5*C4*1.2 -> 39 | E6: =0.5*D4*1.2 -> 45 | F6: =0.5*E4*1.2 -> 54 | G6: =0.5*F4*1.2 -> 66 | H6: =0.5*G4*1.2 -> 72 | I6: =0.5*H4*1.2 -> 69 | J6: =0.5*I4*1.2 -> 48 | ... M6: =0.5*L4*1.2 -> 66 | N6: =SUM(B6:M6) -> 654
A7: Salaires nets (payés mois M) | B7: 20 | C7: 20 | D7: 20 | E7: 20 | F7: 20 | G7: 20 | H7: 20 | I7: 20 | J7: 20 | K7: 20 | L7: 20 | M7: 20 | N7: =SUM(B7:M7) -> 240
A8: Charges sociales URSSAF / Retraite (M+1) | B8: 10 | C8: 10 | D8: 10 | E8: 10 | F8: 10 | G8: 10 | H8: 10 | I8: 10 | J8: 10 | K8: 10 | L8: 10 | M8: 10 | N8: =SUM(B8:M8) -> 120
A9: Autres charges externes TTC | B9: 8 | C9: 8 | D9: 8 | E9: 8 | F9: 8 | G9: 8 | H9: 8 | I9: 8 | J9: 8 | K9: 8 | L9: 8 | M9: 8 | N9: =SUM(B9:M9) -> 96
A10: TVA nette décaissée (le 20 à M+1) | B10: =0.1*'01_Hypotheses_BFR'!$B$16-($B$9-$B$9/1.2) -> 5.1666667 | C10: =0.1*B4-($B$9-$B$9/1.2) -> 4.6666667 | D10: =0.1*C4-($B$9-$B$9/1.2) -> 5.1666667 | E10: =0.1*D4-($B$9-$B$9/1.2) -> 6.1666667 | F10: =0.1*E4-($B$9-$B$9/1.2) -> 7.6666667 | G10: =0.1*F4-($B$9-$B$9/1.2) -> 9.6666667 | H10: =0.1*G4-($B$9-$B$9/1.2) -> 10.666667 | I10: =0.1*H4-($B$9-$B$9/1.2) -> 10.166667 | J10: =0.1*I4-($B$9-$B$9/1.2) -> 6.6666667 | ... M10: =0.1*L4-($B$9-$B$9/1.2) -> 9.6666667 | N10: =SUM(B10:M10) -> 93
A11: Acomptes IS trimestriels | B11: 0 | C11: 0 | D11: 5 | E11: 0 | F11: 0 | G11: 5 | H11: 0 | I11: 0 | J11: 5 | K11: 0 | L11: 0 | M11: 5 | N11: =SUM(B11:M11) -> 20
A12: Investissement matériel comptant (Avril) | B12: 0 | C12: 0 | D12: 0 | E12: 50 | F12: 0 | G12: 0 | H12: 0 | I12: 0 | J12: 0 | K12: 0 | L12: 0 | M12: 0 | N12: =SUM(B12:M12) -> 50
A13: TOTAL DÉCAISSEMENTS TTC | B13: =SUM(B6:B12) -> 82.166667 | C13: =SUM(C6:C12) -> 78.666667 | D13: =SUM(D6:D12) -> 87.166667 | E13: =SUM(E6:E12) -> 139.16667 | F13: =SUM(F6:F12) -> 99.666667 | G13: =SUM(G6:G12) -> 118.66667 | H13: =SUM(H6:H12) -> 120.66667 | I13: =SUM(I6:I12) -> 117.16667 | ... M13: =SUM(M6:M12) -> 118.66667 | N13: =SUM(B13:M13) -> 1273
A14: TRÉSORERIE DE DÉBUT DE MOIS | B14: 25 | C14: =B16 -> 21.433333 | D14: =C16 -> 17.766667 | E14: =D16 -> 9.2 | F14: =E16 -> -39.966667 | G14: =F16 -> -32.233333 | H14: =G16 -> -23.7 | I14: =H16 -> -5.1666667 | J14: =I16 -> 9.0666667 | ... M14: =L16 -> 44.866667 | N14: -
A15: FLUX NET DU MOIS (Encais - Décais) | B15: =B5-B13 -> -3.5666667 | C15: =C5-C13 -> -3.6666667 | D15: =D5-D13 -> -8.5666667 | E15: =E5-E13 -> -49.166667 | F15: =F5-F13 -> 7.7333333 | G15: =G5-G13 -> 8.5333333 | H15: =H5-H13 -> 18.533333 | I15: =I5-I13 -> 14.233333 | ... M15: =M5-M13 -> 9.1333333 | N15: =SUM(B15:M15) -> 29
A16: TRÉSORERIE DE FIN DE MOIS | B16: =B14+B15 -> 21.433333 | C16: =C14+C15 -> 17.766667 | D16: =D14+D15 -> 9.2 | E16: =E14+E15 -> -39.966667 | F16: =F14+F15 -> -32.233333 | G16: =G14+G15 -> -23.7 | H16: =H14+H15 -> -5.1666667 | I16: =I14+I15 -> 9.0666667 | ... M16: =M14+M15 -> 54 | N16: -

Sheet 03_Indicateurs_BFR
A1: DOSSIER 2 (SUITE) - PILOTAGE DU BFR : CRÉANCES, DETTES, DSO, DPO
A3: 1. Suivi mensuel du Besoin en Fonds de Roulement d'exploitation
A4: Indicateur (k€ sauf jours) | B4: Jan | C4: Fév | D4: Mar | E4: Avr | F4: Mai | G4: Juin | H4: Juil | I4: Août | J4: Sep | K4: Oct | L4: Nov | M4: Déc | N4: Moy./Fin d'ex.
A5: Chiffre d'affaires TTC du mois | B5: ='02_Budget_Tresorerie'!B4*1.2 -> 72 | C5: ='02_Budget_Tresorerie'!C4*1.2 -> 78 | D5: ='02_Budget_Tresorerie'!D4*1.2 -> 90 | E5: ='02_Budget_Tresorerie'!E4*1.2 -> 108 | F5: ='02_Budget_Tresorerie'!F4*1.2 -> 132 | G5: ='02_Budget_Tresorerie'!G4*1.2 -> 144 | H5: ='02_Budget_Tresorerie'!H4*1.2 -> 138 | I5: ='02_Budget_Tresorerie'!I4*1.2 -> 96 | ... M5: ='02_Budget_Tresorerie'!M4*1.2 -> 120 | N5: =SUM(B5:M5) -> 1350
A6: Créances clients (fin de mois) | B6: =0.8*B5+0.3*('01_Hypotheses_BFR'!$B$16*1.2) -> 81 | C6: =0.8*C5+0.3*B5 -> 84 | D6: =0.8*D5+0.3*C5 -> 95.4 | E6: =0.8*E5+0.3*D5 -> 113.4 | F6: =0.8*F5+0.3*E5 -> 138 | G6: =0.8*G5+0.3*F5 -> 154.8 | H6: =0.8*H5+0.3*G5 -> 153.6 | I6: =0.8*I5+0.3*H5 -> 118.2 | J6: =0.8*J5+0.3*I5 -> 120 | ... M6: =0.8*M5+0.3*L5 -> 135.6 | N6: =M6 -> 135.6
A7: Dettes fournisseurs (fin de mois) | B7: =0.5*'02_Budget_Tresorerie'!B4*1.2 -> 36 | C7: =0.5*'02_Budget_Tresorerie'!C4*1.2 -> 39 | D7: =0.5*'02_Budget_Tresorerie'!D4*1.2 -> 45 | E7: =0.5*'02_Budget_Tresorerie'!E4*1.2 -> 54 | F7: =0.5*'02_Budget_Tresorerie'!F4*1.2 -> 66 | G7: =0.5*'02_Budget_Tresorerie'!G4*1.2 -> 72 | H7: =0.5*'02_Budget_Tresorerie'!H4*1.2 -> 69 | I7: =0.5*'02_Budget_Tresorerie'!I4*1.2 -> 48 | ... M7: =0.5*'02_Budget_Tresorerie'!M4*1.2 -> 60 | N7: =M7 -> 60
A8: BFR d'exploitation (Créances - Dettes) | B8: =B6-B7 -> 45 | C8: =C6-C7 -> 45 | D8: =D6-D7 -> 50.4 | E8: =E6-E7 -> 59.4 | F8: =F6-F7 -> 72 | G8: =G6-G7 -> 82.8 | H8: =H6-H7 -> 84.6 | I8: =I6-I7 -> 70.2 | ... M8: =M6-M7 -> 75.6 | N8: =M8 -> 75.6
A9: Variation de BFR (besoin de financement complémentaire) | B9: =B8-$B$10 -> -3.6 | C9: =C8-B8 -> 0 | D9: =D8-C8 -> 5.4 | E9: =E8-D8 -> 9 | F9: =F8-E8 -> 12.6 | G9: =G8-F8 -> 10.8 | H9: =H8-G8 -> 1.8 | I9: =I8-H8 -> -14.4 | J9: =J8-I8 -> -7.2 | ... M9: =M8-L8 -> -1.8 | N9: =SUM(B9:M9) -> 27
A10: Repère : BFR au 31/12 N-1 (calculé à partir des hypothèses d'amorçage) | B10: =(0.8*('01_Hypotheses_BFR'!$B$16*1.2)+0.3*('01_Hypotheses_BFR'!$B$15*1.2))-(0.5*'01_Hypotheses_BFR'!$B$16*1.2) -> 48.6
A12: 2. Délais de rotation (DSO / DPO)
A13: Indicateur (jours) | B13: Jan | C13: Fév | D13: Mar | E13: Avr | F13: Mai | G13: Juin | H13: Juil | I13: Août | J13: Sep | K13: Oct | L13: Nov | M13: Déc
A14: DSO - Délai de paiement clients (jours, base 30) | B14: =B6/B5*30 -> 33.75 | C14: =C6/C5*30 -> 32.307692 | D14: =D6/D5*30 -> 31.8 | E14: =E6/E5*30 -> 31.5 | F14: =F6/F5*30 -> 31.363636 | G14: =G6/G5*30 -> 32.25 | H14: =H6/H5*30 -> 33.391304 | I14: =I6/I5*30 -> 36.9375 | ... M14: =M6/M5*30 -> 33.9 | N14: =AVERAGE(B14:M14) -> 32.792737
A15: DPO - Délai de règlement fournisseurs (jours, base 30) | B15: =B7/(0.5*'02_Budget_Tresorerie'!B4*1.2)*30 -> 30 | C15: =C7/(0.5*'02_Budget_Tresorerie'!C4*1.2)*30 -> 30 | D15: =D7/(0.5*'02_Budget_Tresorerie'!D4*1.2)*30 -> 30 | E15: =E7/(0.5*'02_Budget_Tresorerie'!E4*1.2)*30 -> 30 | F15: =F7/(0.5*'02_Budget_Tresorerie'!F4*1.2)*30 -> 30 | G15: =G7/(0.5*'02_Budget_Tresorerie'!G4*1.2)*30 -> 30 | H15: =H7/(0.5*'02_Budget_Tresorerie'!H4*1.2)*30 -> 30 | I15: =I7/(0.5*'02_Budget_Tresorerie'!I4*1.2)*30 -> 30 | ... M15: =M7/(0.5*'02_Budget_Tresorerie'!M4*1.2)*30 -> 30 | N15: =AVERAGE(B15:M15) -> 30
A17: Note de lecture : le DSO théorique pondéré par les hypothèses (20 % à 0 j, 50 % à 30 j, 30 % à 60 j) est de 33 jours. Le DSO calculé ici en stock/flux fin de mois s'en écarte légèrement en période de forte croissance du CA, ce qui est normal et doit être commenté comme tel dans le portfolio.

Sheet 04_Scenario_Financement
A1: DOSSIER 2 (SUITE) - SCÉNARIO DE FINANCEMENT CORRIGÉ (EMPRUNT MOYEN TERME SUR L'INVESTISSEMENT)
A3: 1. Hypothèses de financement
A4: Montant emprunté (k€) | B4: 50
A5: Taux d'intérêt annuel | B5: 0.04
A6: Durée de l'emprunt (mois) | B6: 48
A7: Mensualité (capital + intérêts, k€) | B7: =-PMT(B5/12,B6,B4) -> 1.1289527
A8: Premier remboursement | B8: Mai (mois suivant le décaissement de l'équipement en avril)
A10: 2. Comparatif de trésorerie de fin de mois : baseline vs scénario financement
A11: Poste (k€) | B11: Jan | C11: Fév | D11: Mar | E11: Avr | F11: Mai | G11: Juin | H11: Juil | I11: Août | J11: Sep | K11: Oct | L11: Nov | M11: Déc
A12: Trésorerie fin de mois - Situation actuelle (baseline) | B12: ='02_Budget_Tresorerie'!B16 -> 21.433333 | C12: ='02_Budget_Tresorerie'!C16 -> 17.766667 | D12: ='02_Budget_Tresorerie'!D16 -> 9.2 | E12: ='02_Budget_Tresorerie'!E16 -> -39.966667 | F12: ='02_Budget_Tresorerie'!F16 -> -32.233333 | G12: ='02_Budget_Tresorerie'!G16 -> -23.7 | H12: ='02_Budget_Tresorerie'!H16 -> -5.1666667 | I12: ='02_Budget_Tresorerie'!I16 -> 9.0666667 | ... M12: ='02_Budget_Tresorerie'!M16 -> 54
A13: Emprunt bancaire MT mobilisé | B13: 0 | C13: 0 | D13: 0 | E13: =$B$4 -> 50 | F13: 0 | G13: 0 | H13: 0 | I13: 0 | J13: 0 | K13: 0 | L13: 0 | M13: 0
A14: Remboursement emprunt (capital + intérêts) | B14: 0 | C14: 0 | D14: 0 | E14: 0 | F14: =-$B$7 -> -1.1289527 | G14: =-$B$7 -> -1.1289527 | H14: =-$B$7 -> -1.1289527 | I14: =-$B$7 -> -1.1289527 | J14: =-$B$7 -> -1.1289527 | K14: =-$B$7 -> -1.1289527 | L14: =-$B$7 -> -1.1289527 | M14: =-$B$7 -> -1.1289527
A15: Cumul de l'ajustement de financement | B15: =B13+B14 -> 0 | C15: =B15+C13+C14 -> 0 | D15: =C15+D13+D14 -> 0 | E15: =D15+E13+E14 -> 50 | F15: =E15+F13+F14 -> 48.871047 | G15: =F15+G13+G14 -> 47.742095 | H15: =G15+H13+H14 -> 46.613142 | I15: =H15+I13+I14 -> 45.484189 | J15: =I15+J13+J14 -> 44.355236 | ... M15: =L15+M13+M14 -> 40.968378
A16: Trésorerie fin de mois - Scénario financement corrigé | B16: =B12+B15 -> 21.433333 | C16: =C12+C15 -> 17.766667 | D16: =D12+D15 -> 9.2 | E16: =E12+E15 -> 10.033333 | F16: =F12+F15 -> 16.637714 | G16: =G12+G15 -> 24.042095 | H16: =H12+H15 -> 41.446475 | I16: =I12+I15 -> 54.550856 | ... M16: =M12+M15 -> 94.968378
A18: Note : La mise en place de l’emprunt bancaire permet de résorber intégralement l’impasse de trésorerie constatée en avril, en portant le solde à +10,0 k€. Les échéances mensuelles de remboursement sont ensuite absorbées par les flux de trésorerie générés par l’activité, sans entraîner de retour à une situation déficitaire. Cette évolution témoigne de l’efficacité du financement à moyen terme dans la sécurisation de la liquidité, grâce à la marge de sécurité constituée dès le mois de mai.
